pedros/__init__.py
pedros/has_dep.py
pedros/logger.py
pedros/progbar.py
pedros/decorators/__init__.py
pedros/decorators/safe.py
pedros/decorators/timed.py
pedros/decorators/universal_decorator.py
pedros-0.12.2.dist-info/METADATA
pedros-0.12.2.dist-info/WHEEL
pedros-0.12.2.dist-info/licenses/LICENSE
pedros-0.12.2.dist-info/RECORD
