Metadata-Version: 2.4
Name: pedros
Version: 0.12.2
Summary: Small utility package for my projects.
Author: Pierre LAPOLLA
License: MIT License
License-File: LICENSE
Requires-Python: >=3.10
Requires-Dist: wrapt>=2.0.1
